cagey/__init__.py
cagey/ms.py
cagey/nmr.py
cagey/py.typed
cagey/queries.py
cagey/reactions.py
cagey/turbidity.py
cagey/_internal/__init__.py
cagey/_internal/ms.py
cagey/_internal/mzmine3.conf
cagey/_internal/nmr.py
cagey/_internal/queries.py
cagey/_internal/reactions.py
cagey/_internal/turbidity.py
cagey/_internal/types.py
cagey/_internal/scripts/__init__.py
cagey/_internal/scripts/add_ms.py
cagey/_internal/scripts/add_nmr.py
cagey/_internal/scripts/add_turbidity.py
cagey/_internal/scripts/cagey.py
cagey/_internal/scripts/cagey_insert.py
cagey/_internal/scripts/cagey_new.py
cagey/_internal/scripts/ms.py
cagey/_internal/scripts/mzmine_input_template.xml
cagey/_internal/scripts/nmr.py
cagey/_internal/sql/create_tables.sql
cagey-1.0.4.dist-info/METADATA
cagey-1.0.4.dist-info/WHEEL
cagey-1.0.4.dist-info/entry_points.txt
cagey-1.0.4.dist-info/top_level.txt
cagey-1.0.4.dist-info/RECORD
