Metadata-Version: 2.1
Name: cagey
Version: 1.0.4
Summary: Streamlined automated data analysis.
Maintainer-email: Lukas Turcani <lukasturcani93@gmail.com>
Project-URL: github, https://github.com/lukasturcani/cagey
Project-URL: documentation, https://cagey.readthedocs.io
Requires-Python: ==3.11.*
Requires-Dist: polars[connectorx,pyarrow]
Requires-Dist: nmrglue
Requires-Dist: pyopenms
Requires-Dist: rdkit
Requires-Dist: typer[all]
Requires-Dist: rich
Provides-Extra: dev
Requires-Dist: ruff ; extra == 'dev'
Requires-Dist: mypy ; extra == 'dev'
Requires-Dist: pytest ; extra == 'dev'
Requires-Dist: pytest-cov ; extra == 'dev'
Requires-Dist: pytest-datadir ; extra == 'dev'
Requires-Dist: sphinx ; extra == 'dev'
Requires-Dist: sphinx-copybutton ; extra == 'dev'
Requires-Dist: build ; extra == 'dev'
Requires-Dist: twine ; extra == 'dev'
Requires-Dist: furo ; extra == 'dev'
Requires-Dist: sqlfluff ; extra == 'dev'
